smpmgr/__init__.py
smpmgr/__main__.py
smpmgr/common.py
smpmgr/enumeration_management.py
smpmgr/file_management.py
smpmgr/image_management.py
smpmgr/logging.py
smpmgr/main.py
smpmgr/os_management.py
smpmgr/plugins.py
smpmgr/py.typed
smpmgr/shell_management.py
smpmgr/stat_management.py
smpmgr/terminal.py
smpmgr/user/__init__.py
smpmgr/user/intercreate.py
smpmgr-0.17.0.dist-info/METADATA
smpmgr-0.17.0.dist-info/WHEEL
smpmgr-0.17.0.dist-info/entry_points.txt
smpmgr-0.17.0.dist-info/licenses/LICENSE
smpmgr-0.17.0.dist-info/RECORD
