Metadata-Version: 2.4
Name: smpmgr
Version: 0.17.0
Summary: Simple Management Protocol (SMP) Manager for remotely managing MCU firmware
License-Expression: Apache-2.0
License-File: LICENSE
Author: JP Hutchins
Author-email: jp@intercreate.io
Requires-Python: >=3.10,<4
Classifier: Programming Language :: Python :: 3
Classifier: Programming Language :: Python :: 3.10
Classifier: Programming Language :: Python :: 3.11
Classifier: Programming Language :: Python :: 3.12
Classifier: Programming Language :: Python :: 3.13
Classifier: Programming Language :: Python :: 3.14
Requires-Dist: readchar (>=4.0.5,<5.0.0)
Requires-Dist: smpclient (>=6.0.0,<7.0.0)
Requires-Dist: typer[all] (>=0.16.0,<0.17.0)
